{"header" : {
  "cloc_url"           : "github.com/AlDanial/cloc",
  "cloc_version"       : "1.98",
  "elapsed_seconds"    : 2.22044706344604,
  "n_files"            : 1115,
  "n_lines"            : 256577,
  "files_per_second"   : 502.151129092699,
  "lines_per_second"   : 115551.955380464},
"Text" :{
  "nFiles": 20,
  "blank": 15034,
  "comment": 0,
  "code": 120337},
"JSON" :{
  "nFiles": 23,
  "blank": 0,
  "comment": 0,
  "code": 21538},
"XML" :{
  "nFiles": 215,
  "blank": 71,
  "comment": 1415,
  "code": 18869},
"CSS" :{
  "nFiles": 52,
  "blank": 2485,
  "comment": 97,
  "code": 11367},
"Python" :{
  "nFiles": 99,
  "blank": 2621,
  "comment": 4904,
  "code": 8309},
"JavaScript" :{
  "nFiles": 72,
  "blank": 1211,
  "comment": 280,
  "code": 6906},
"JSX" :{
  "nFiles": 26,
  "blank": 594,
  "comment": 19,
  "code": 5585},
"HTML" :{
  "nFiles": 51,
  "blank": 1054,
  "comment": 5,
  "code": 4953},
"Java" :{
  "nFiles": 103,
  "blank": 1166,
  "comment": 836,
  "code": 3067},
"Kotlin" :{
  "nFiles": 73,
  "blank": 450,
  "comment": 411,
  "code": 3013},
"PHP" :{
  "nFiles": 58,
  "blank": 421,
  "comment": 79,
  "code": 2319},
"SQL" :{
  "nFiles": 24,
  "blank": 585,
  "comment": 272,
  "code": 1653},
"Bourne Shell" :{
  "nFiles": 13,
  "blank": 288,
  "comment": 507,
  "code": 1511},
"C" :{
  "nFiles": 8,
  "blank": 321,
  "comment": 271,
  "code": 1459},
"C++" :{
  "nFiles": 6,
  "blank": 144,
  "comment": 70,
  "code": 1085},
"Gradle" :{
  "nFiles": 37,
  "blank": 102,
  "comment": 56,
  "code": 1013},
"Properties" :{
  "nFiles": 51,
  "blank": 0,
  "comment": 357,
  "code": 872},
"CSV" :{
  "nFiles": 3,
  "blank": 0,
  "comment": 0,
  "code": 852},
"C/C++ Header" :{
  "nFiles": 14,
  "blank": 217,
  "comment": 334,
  "code": 826},
"SVG" :{
  "nFiles": 93,
  "blank": 4,
  "comment": 7,
  "code": 804},
"DOS Batch" :{
  "nFiles": 12,
  "blank": 254,
  "comment": 24,
  "code": 790},
"Markdown" :{
  "nFiles": 15,
  "blank": 217,
  "comment": 4,
  "code": 573},
"TOML" :{
  "nFiles": 12,
  "blank": 30,
  "comment": 0,
  "code": 301},
"YAML" :{
  "nFiles": 5,
  "blank": 29,
  "comment": 9,
  "code": 201},
"PowerShell" :{
  "nFiles": 2,
  "blank": 13,
  "comment": 9,
  "code": 118},
"Maven" :{
  "nFiles": 6,
  "blank": 0,
  "comment": 0,
  "code": 82},
"Ant" :{
  "nFiles": 8,
  "blank": 104,
  "comment": 440,
  "code": 40},
"CMake" :{
  "nFiles": 1,
  "blank": 11,
  "comment": 0,
  "code": 35},
"INI" :{
  "nFiles": 2,
  "blank": 3,
  "comment": 13,
  "code": 20},
"ProGuard" :{
  "nFiles": 11,
  "blank": 33,
  "comment": 198,
  "code": 0},
"SUM": {
  "blank": 27462,
  "comment": 10617,
  "code": 218498,
  "nFiles": 1115} }
